examples/reference.py
examples/pip/pip_flow.py
examples/poetry/poetry_flow.py
plugins/__init__.py
plugins/pip/__init__.py
plugins/pip/plugin.py
plugins/poetry/__init__.py
plugins/poetry/plugin.py
ml_plugins-0.0.17.dist-info/METADATA
ml_plugins-0.0.17.dist-info/WHEEL
ml_plugins-0.0.17.dist-info/top_level.txt
ml_plugins-0.0.17.dist-info/RECORD
