Metadata-Version: 2.1
Name: ml-plugins
Version: 0.0.17
Requires-Dist: metaflow (==2.9.2)
Requires-Dist: poetry
